dotfile_sync/__init__.py
dotfile_sync/main.py
dotfile_sync-0.0.6.dist-info/METADATA
dotfile_sync-0.0.6.dist-info/WHEEL
dotfile_sync-0.0.6.dist-info/entry_points.txt
dotfile_sync-0.0.6.dist-info/RECORD
