Metadata-Version: 2.3
Name: dotfile_sync
Version: 0.0.6
Summary: dotfile sycn auxiliary tool for scp
Project-URL: Homepage, https://github.com/aquanjsw/dotfile-sync
Author-email: aquanjsw <zhdlcc@gmail.com>
Classifier: Operating System :: OS Independent
Classifier: Programming Language :: Python :: 3
Requires-Python: >=3.8
Requires-Dist: pyyaml
